ogrep/__init__.py
ogrep/__main__.py
ogrep/ast_chunking.py
ogrep/chunking.py
ogrep/cli.py
ogrep/db.py
ogrep/embed.py
ogrep/filetype.py
ogrep/indexer.py
ogrep/models.py
ogrep/rerank.py
ogrep/search.py
ogrep/commands/__init__.py
ogrep/commands/_arg_builders.py
ogrep/commands/_common.py
ogrep/commands/benchmark.py
ogrep/commands/chunk.py
ogrep/commands/clean.py
ogrep/commands/delete.py
ogrep/commands/device.py
ogrep/commands/health.py
ogrep/commands/index.py
ogrep/commands/log.py
ogrep/commands/models.py
ogrep/commands/query.py
ogrep/commands/reindex.py
ogrep/commands/reset.py
ogrep/commands/status.py
ogrep/commands/tune.py
ogrep/mcp/__init__.py
ogrep/mcp/__main__.py
ogrep-0.7.2.dist-info/METADATA
ogrep-0.7.2.dist-info/WHEEL
ogrep-0.7.2.dist-info/entry_points.txt
ogrep-0.7.2.dist-info/licenses/LICENSE
ogrep-0.7.2.dist-info/RECORD
