Metadata-Version: 2.4
Name: ogrep
Version: 0.7.2
Summary: Semantic grep for codebases - local-first, SQLite-backed, with local or cloud embeddings
Project-URL: Homepage, https://github.com/gplv2/ogrep-marketplace
Project-URL: Repository, https://github.com/gplv2/ogrep-marketplace
Project-URL: Documentation, https://github.com/gplv2/ogrep-marketplace#readme
Project-URL: Changelog, https://github.com/gplv2/ogrep-marketplace/blob/main/CHANGELOG.md
Project-URL: Issues, https://github.com/gplv2/ogrep-marketplace/issues
Author-email: Glenn Plas <info@bitless.be>
License: MIT
License-File: LICENSE
Keywords: claude-code,code-search,developer-tools,embeddings,grep,lm-studio,local-embeddings,openai,semantic-search,sqlite
Classifier: Development Status :: 4 - Beta
Classifier: Environment :: Console
Classifier: Intended Audience :: Developers
Classifier: License :: OSI Approved :: MIT License
Classifier: Operating System :: OS Independent
Classifier: Programming Language :: Python :: 3
Classifier: Programming Language :: Python :: 3.10
Classifier: Programming Language :: Python :: 3.11
Classifier: Programming Language :: Python :: 3.12
Classifier: Topic :: Software Development
Classifier: Topic :: Text Processing :: Indexing
Classifier: Topic :: Utilities
Requires-Python: >=3.10
Requires-Dist: openai>=1.0.0
Requires-Dist: python-dotenv>=1.0.0
Requires-Dist: tqdm>=4.0.0
Provides-Extra: ast
Requires-Dist: tree-sitter-go>=0.23.0; extra == 'ast'
Requires-Dist: tree-sitter-javascript>=0.23.0; extra == 'ast'
Requires-Dist: tree-sitter-python>=0.23.0; extra == 'ast'
Requires-Dist: tree-sitter-rust>=0.23.0; extra == 'ast'
Requires-Dist: tree-sitter-typescript>=0.23.0; extra == 'ast'
Requires-Dist: tree-sitter>=0.23.0; extra == 'ast'
Provides-Extra: ast-all
Requires-Dist: tree-sitter-bash>=0.23.0; extra == 'ast-all'
Requires-Dist: tree-sitter-c-sharp>=0.23.0; extra == 'ast-all'
Requires-Dist: tree-sitter-c>=0.23.0; extra == 'ast-all'
Requires-Dist: tree-sitter-cpp>=0.22.0; extra == 'ast-all'
Requires-Dist: tree-sitter-go>=0.23.0; extra == 'ast-all'
Requires-Dist: tree-sitter-java>=0.23.0; extra == 'ast-all'
Requires-Dist: tree-sitter-javascript>=0.23.0; extra == 'ast-all'
Requires-Dist: tree-sitter-python>=0.23.0; extra == 'ast-all'
Requires-Dist: tree-sitter-ruby>=0.23.0; extra == 'ast-all'
Requires-Dist: tree-sitter-rust>=0.23.0; extra == 'ast-all'
Requires-Dist: tree-sitter-typescript>=0.23.0; extra == 'ast-all'
Requires-Dist: tree-sitter>=0.23.0; extra == 'ast-all'
Provides-Extra: dev
Requires-Dist: mypy>=1.0.0; extra == 'dev'
Requires-Dist: pre-commit>=3.0.0; extra == 'dev'
Requires-Dist: pytest-cov>=4.0.0; extra == 'dev'
Requires-Dist: pytest>=8.0.0; extra == 'dev'
Requires-Dist: ruff>=0.1.0; extra == 'dev'
Requires-Dist: yamllint>=1.35.0; extra == 'dev'
Provides-Extra: mcp
Requires-Dist: mcp>=1.0.0; extra == 'mcp'
Provides-Extra: rerank
Requires-Dist: sentence-transformers>=2.2.0; extra == 'rerank'
Provides-Extra: speed
Requires-Dist: numpy>=1.24.0; extra == 'speed'
